fitconnect/__init__.py
fitconnect/fitconnect.py
fitconnect/schema/metadata.schema.v1.0.0.json
fitconnect-0.4.2.dist-info/LICENSE.txt
fitconnect-0.4.2.dist-info/WHEEL
fitconnect-0.4.2.dist-info/METADATA
fitconnect-0.4.2.dist-info/RECORD
