Metadata-Version: 2.1
Name: fitconnect
Version: 0.4.2
Summary: 
License: EUPL-1.2
Author: Your Name
Author-email: you@example.com
Requires-Python: >=3.7,<4.0
Classifier: License :: OSI Approved :: European Union Public Licence 1.2 (EUPL 1.2)
Classifier: Programming Language :: Python :: 3
Classifier: Programming Language :: Python :: 3.10
Classifier: Programming Language :: Python :: 3.7
Classifier: Programming Language :: Python :: 3.8
Classifier: Programming Language :: Python :: 3.9
Requires-Dist: jsonschema (>=4.4.0,<5.0.0)
Requires-Dist: jwcrypto (>=1.1,<2.0)
Requires-Dist: requests (>=2.26.0,<3.0.0)
Requires-Dist: semver (>=3.0.0.dev3,<4.0.0)
Requires-Dist: strictyaml (>=1.6.1,<2.0.0)
